{
"meta":{"test_sets":[],"test_metrics":[],"learn_metrics":[{"best_value":"Min","name":"MultiClass"}],"launch_mode":"Train","parameters":"","iteration_count":256,"learn_sets":["learn"],"name":"experiment"},
"iterations":[
{"learn":[1.084351123],"iteration":0,"passed_time":0.0126113152,"remaining_time":3.215885376},
{"learn":[0.8367502482],"iteration":1,"passed_time":0.01667367428,"remaining_time":2.117556634},
{"learn":[0.7018102702],"iteration":2,"passed_time":0.02035864762,"remaining_time":1.716912616},
{"learn":[0.6118757183],"iteration":3,"passed_time":0.02385724578,"remaining_time":1.503006484},
{"learn":[0.5367293478],"iteration":4,"passed_time":0.02771640053,"remaining_time":1.391363306},
{"learn":[0.4795187873],"iteration":5,"passed_time":0.03150019351,"remaining_time":1.312508063},
{"learn":[0.434252759],"iteration":6,"passed_time":0.03463890424,"remaining_time":1.232155308},
{"learn":[0.3957972908],"iteration":7,"passed_time":0.0383450865,"remaining_time":1.188697682},
{"learn":[0.3726553816],"iteration":8,"passed_time":0.04163935446,"remaining_time":1.14276895},
{"learn":[0.3460192874],"iteration":9,"passed_time":0.04545377366,"remaining_time":1.118162832},
{"learn":[0.321499711],"iteration":10,"passed_time":0.04920558,"remaining_time":1.095942464},
{"learn":[0.298935009],"iteration":11,"passed_time":0.05305925814,"remaining_time":1.078871582},
{"learn":[0.2827654719],"iteration":12,"passed_time":0.05643911768,"remaining_time":1.054977354},
{"learn":[0.2654426797],"iteration":13,"passed_time":0.06057561974,"remaining_time":1.047092856},
{"learn":[0.248407806],"iteration":14,"passed_time":0.06399604581,"remaining_time":1.028203136},
{"learn":[0.2386387665],"iteration":15,"passed_time":0.06747238691,"remaining_time":1.012085804},
{"learn":[0.2273922999],"iteration":16,"passed_time":0.07093866023,"remaining_time":0.9973141055},
{"learn":[0.2182200485],"iteration":17,"passed_time":0.07472928713,"remaining_time":0.9880872409},
{"learn":[0.2083001152],"iteration":18,"passed_time":0.07824915571,"remaining_time":0.976055258},
{"learn":[0.198234431],"iteration":19,"passed_time":0.08180106102,"remaining_time":0.96525252},
{"learn":[0.1884325316],"iteration":20,"passed_time":0.08553108704,"remaining_time":0.9571335931},
{"learn":[0.1805933475],"iteration":21,"passed_time":0.08930771411,"remaining_time":0.9499093228},
{"learn":[0.1729250281],"iteration":22,"passed_time":0.09303552434,"remaining_time":0.9424903118},
{"learn":[0.1656648744],"iteration":23,"passed_time":0.09657321736,"remaining_time":0.9335411011},
{"learn":[0.1600689049],"iteration":24,"passed_time":0.1002524201,"remaining_time":0.9263323617},
{"learn":[0.1539788472],"iteration":25,"passed_time":0.1045721243,"remaining_time":0.9250610993},
{"learn":[0.1490515401],"iteration":26,"passed_time":0.1124091202,"remaining_time":0.9533958715},
{"learn":[0.1432189019],"iteration":27,"passed_time":0.1170139895,"remaining_time":0.9528282002},
{"learn":[0.139835964],"iteration":28,"passed_time":0.121255885,"remaining_time":0.9491408929},
{"learn":[0.1368237581],"iteration":29,"passed_time":0.1246435572,"remaining_time":0.9389814639},
{"learn":[0.132880633],"iteration":30,"passed_time":0.128224219,"remaining_time":0.9306596543},
{"learn":[0.1294979058],"iteration":31,"passed_time":0.1326672395,"remaining_time":0.9286706768},
{"learn":[0.1236782935],"iteration":32,"passed_time":0.1365677146,"remaining_time":0.9228666775},
{"learn":[0.1193753861],"iteration":33,"passed_time":0.1411680038,"remaining_time":0.9217440245},
{"learn":[0.1162575398],"iteration":34,"passed_time":0.1443965031,"remaining_time":0.9117607766},
{"learn":[0.1134081576],"iteration":35,"passed_time":0.1482975229,"remaining_time":0.9062626402},
{"learn":[0.1110022248],"iteration":36,"passed_time":0.1523443946,"remaining_time":0.9017141196},
{"learn":[0.1078622471],"iteration":37,"passed_time":0.156147359,"remaining_time":0.8957927438},
{"learn":[0.1054125785],"iteration":38,"passed_time":0.1597251453,"remaining_time":0.8887270903},
{"learn":[0.1031946042],"iteration":39,"passed_time":0.1636588651,"remaining_time":0.8837578718},
{"learn":[0.1015133157],"iteration":40,"passed_time":0.1674838973,"remaining_time":0.8782692174},
{"learn":[0.09869196649],"iteration":41,"passed_time":0.1710925906,"remaining_time":0.8717574854},
{"learn":[0.09678708788],"iteration":42,"passed_time":0.1752994283,"remaining_time":0.8683436797},
{"learn":[0.09575362668],"iteration":43,"passed_time":0.1783994715,"remaining_time":0.85956109},
{"learn":[0.09403649585],"iteration":44,"passed_time":0.1820416511,"remaining_time":0.8535730753},
{"learn":[0.09277365881],"iteration":45,"passed_time":0.1854015644,"remaining_time":0.8463984462},
{"learn":[0.08991655167],"iteration":46,"passed_time":0.188984287,"remaining_time":0.8403769357},
{"learn":[0.08827542102],"iteration":47,"passed_time":0.1924753551,"remaining_time":0.8340598721},
{"learn":[0.08718358043],"iteration":48,"passed_time":0.1965710433,"remaining_time":0.8304123665},
{"learn":[0.08372990113],"iteration":49,"passed_time":0.2008421825,"remaining_time":0.8274697917},
{"learn":[0.08212843306],"iteration":50,"passed_time":0.2046732978,"remaining_time":0.8227063932},
{"learn":[0.08053387314],"iteration":51,"passed_time":0.2088011184,"remaining_time":0.8191428492},
{"learn":[0.07922524524],"iteration":52,"passed_time":0.2132077781,"remaining_time":0.8166260178},
{"learn":[0.07850220812],"iteration":53,"passed_time":0.2170697563,"remaining_time":0.8120016808},
{"learn":[0.07708861957],"iteration":54,"passed_time":0.2208870787,"remaining_time":0.8072418695},
{"learn":[0.0761807012],"iteration":55,"passed_time":0.2244710487,"remaining_time":0.8016823169},
{"learn":[0.07556186595],"iteration":56,"passed_time":0.2281242458,"remaining_time":0.7964337705},
{"learn":[0.0742249784],"iteration":57,"passed_time":0.2315830737,"remaining_time":0.7905767},
{"learn":[0.07186435692],"iteration":58,"passed_time":0.2363875356,"remaining_time":0.7892939746},
{"learn":[0.07105286282],"iteration":59,"passed_time":0.2405099383,"remaining_time":0.7856657984},
{"learn":[0.06957601017],"iteration":60,"passed_time":0.2440574904,"remaining_time":0.7801837809},
{"learn":[0.06926423186],"iteration":61,"passed_time":0.2477057951,"remaining_time":0.7750794233},
{"learn":[0.06873140333],"iteration":62,"passed_time":0.2511132173,"remaining_time":0.7692833482},
{"learn":[0.06769755219],"iteration":63,"passed_time":0.2545072573,"remaining_time":0.763521772},
{"learn":[0.06596696866],"iteration":64,"passed_time":0.258361843,"remaining_time":0.7591863387},
{"learn":[0.0647262103],"iteration":65,"passed_time":0.262509109,"remaining_time":0.7557080409},
{"learn":[0.06371434826],"iteration":66,"passed_time":0.2699389227,"remaining_time":0.7614694985},
{"learn":[0.06227735315],"iteration":67,"passed_time":0.2743128996,"remaining_time":0.7583944872},
{"learn":[0.06135119748],"iteration":68,"passed_time":0.2783380169,"remaining_time":0.7543363647},
{"learn":[0.06021672766],"iteration":69,"passed_time":0.2824824518,"remaining_time":0.7505962291},
{"learn":[0.05983064064],"iteration":70,"passed_time":0.2859996372,"remaining_time":0.7452103223},
{"learn":[0.05899508658],"iteration":71,"passed_time":0.2900912323,"remaining_time":0.7413442604},
{"learn":[0.05840323579],"iteration":72,"passed_time":0.2938315735,"remaining_time":0.7365914788},
{"learn":[0.05758498109],"iteration":73,"passed_time":0.2976485491,"remaining_time":0.7320545397},
{"learn":[0.05636085287],"iteration":74,"passed_time":0.3012469518,"remaining_time":0.7270093104},
{"learn":[0.05590114216],"iteration":75,"passed_time":0.3052621274,"remaining_time":0.7229892492},
{"learn":[0.05531187337],"iteration":76,"passed_time":0.308963657,"remaining_time":0.7182401897},
{"learn":[0.05467503266],"iteration":77,"passed_time":0.312667505,"remaining_time":0.7135232806},
{"learn":[0.05416191685],"iteration":78,"passed_time":0.3165238128,"remaining_time":0.7091736058},
{"learn":[0.05303730076],"iteration":79,"passed_time":0.3203188592,"remaining_time":0.7047014902},
{"learn":[0.05225999436],"iteration":80,"passed_time":0.3243404773,"remaining_time":0.7007355991},
{"learn":[0.0513225148],"iteration":81,"passed_time":0.3281382977,"remaining_time":0.696293461},
{"learn":[0.05091341643],"iteration":82,"passed_time":0.332013001,"remaining_time":0.6920270985},
{"learn":[0.05034371809],"iteration":83,"passed_time":0.3363576613,"remaining_time":0.6887323542},
{"learn":[0.04989863516],"iteration":84,"passed_time":0.3403892947,"remaining_time":0.6847831694},
{"learn":[0.0496525923],"iteration":85,"passed_time":0.3445062271,"remaining_time":0.6810006814},
{"learn":[0.04885697482],"iteration":86,"passed_time":0.3478651558,"remaining_time":0.6757380612},
{"learn":[0.04833965932],"iteration":87,"passed_time":0.3519417493,"remaining_time":0.671888794},
{"learn":[0.04783702957],"iteration":88,"passed_time":0.3556841169,"remaining_time":0.6674072755},
{"learn":[0.04740206384],"iteration":89,"passed_time":0.3592667203,"remaining_time":0.6626475063},
{"learn":[0.04671820451],"iteration":90,"passed_time":0.363245573,"remaining_time":0.6586320829},
{"learn":[0.04642543811],"iteration":91,"passed_time":0.3669111227,"remaining_time":0.6540589579},
{"learn":[0.04599048292],"iteration":92,"passed_time":0.3712703377,"remaining_time":0.6507211295},
{"learn":[0.04561727952],"iteration":93,"passed_time":0.3753269635,"remaining_time":0.646840086},
{"learn":[0.04451800912],"iteration":94,"passed_time":0.3793712252,"remaining_time":0.6429343922},
{"learn":[0.04426203348],"iteration":95,"passed_time":0.3831453785,"remaining_time":0.6385756308},
{"learn":[0.04388855871],"iteration":96,"passed_time":0.3869827529,"remaining_time":0.6343325537},
{"learn":[0.04344273807],"iteration":97,"passed_time":0.3914543624,"remaining_time":0.6311202986},
{"learn":[0.04289609061],"iteration":98,"passed_time":0.3959353212,"remaining_time":0.6278974285},
{"learn":[0.04264147447],"iteration":99,"passed_time":0.3998198539,"remaining_time":0.623718972},
{"learn":[0.04204088442],"iteration":100,"passed_time":0.4038004484,"remaining_time":0.6196937574},
{"learn":[0.04189639555],"iteration":101,"passed_time":0.4073086487,"remaining_time":0.614956195},
{"learn":[0.04178337803],"iteration":102,"passed_time":0.4111803216,"remaining_time":0.6107824194},
{"learn":[0.04145607878],"iteration":103,"passed_time":0.4148692128,"remaining_time":0.606347311},
{"learn":[0.04077202712],"iteration":104,"passed_time":0.4187372735,"remaining_time":0.6021840791},
{"learn":[0.04038149539],"iteration":105,"passed_time":0.4221081099,"remaining_time":0.5973227971},
{"learn":[0.03984871164],"iteration":106,"passed_time":0.4260408895,"remaining_time":0.5932718928},
{"learn":[0.03933270558],"iteration":107,"passed_time":0.4296742014,"remaining_time":0.5888127946},
{"learn":[0.03868226462],"iteration":108,"passed_time":0.4334602054,"remaining_time":0.5845747724},
{"learn":[0.03824422158],"iteration":109,"passed_time":0.4376516925,"remaining_time":0.5808831555},
{"learn":[0.03776325686],"iteration":110,"passed_time":0.4413374331,"remaining_time":0.5765218721},
{"learn":[0.03729855079],"iteration":111,"passed_time":0.4450717352,"remaining_time":0.5722350882},
{"learn":[0.03702833203],"iteration":112,"passed_time":0.448899396,"remaining_time":0.5680762268},
{"learn":[0.0368334943],"iteration":113,"passed_time":0.4541211561,"remaining_time":0.5656596857},
{"learn":[0.03644135278],"iteration":114,"passed_time":0.4583193455,"remaining_time":0.5619393715},
{"learn":[0.03625013247],"iteration":115,"passed_time":0.4620658919,"remaining_time":0.5576657316},
{"learn":[0.0359600877],"iteration":116,"passed_time":0.4664400943,"remaining_time":0.5541467788},
{"learn":[0.0356593013],"iteration":117,"passed_time":0.4707264819,"remaining_time":0.5505106313},
{"learn":[0.03524660659],"iteration":118,"passed_time":0.4742367006,"remaining_time":0.5459699831},
{"learn":[0.034987688],"iteration":119,"passed_time":0.4778566412,"remaining_time":0.54157086},
{"learn":[0.03466000936],"iteration":120,"passed_time":0.4815038241,"remaining_time":0.5372150104},
{"learn":[0.03385405864],"iteration":121,"passed_time":0.4852526042,"remaining_time":0.5329823686},
{"learn":[0.03349732731],"iteration":122,"passed_time":0.4892190555,"remaining_time":0.5289929625},
{"learn":[0.03312159725],"iteration":123,"passed_time":0.4939432352,"remaining_time":0.5258105407},
{"learn":[0.03301375425],"iteration":124,"passed_time":0.4979749007,"remaining_time":0.5218776959},
{"learn":[0.03280041311],"iteration":125,"passed_time":0.501883727,"remaining_time":0.5178165437},
{"learn":[0.03259481532],"iteration":126,"passed_time":0.5059791598,"remaining_time":0.5139473356},
{"learn":[0.03249867823],"iteration":127,"passed_time":0.5098688043,"remaining_time":0.5098688043},
{"learn":[0.03235306963],"iteration":128,"passed_time":0.5181114172,"remaining_time":0.510078682},
{"learn":[0.03218368297],"iteration":129,"passed_time":0.5230430102,"remaining_time":0.5069493792},
{"learn":[0.03183876821],"iteration":130,"passed_time":0.5307094048,"remaining_time":0.5064021038},
{"learn":[0.03167093075],"iteration":131,"passed_time":0.5346190695,"remaining_time":0.5022179138},
{"learn":[0.03144738811],"iteration":132,"passed_time":0.5389853865,"remaining_time":0.4984601694},
{"learn":[0.03120716526],"iteration":133,"passed_time":0.5431421281,"remaining_time":0.4945025345},
{"learn":[0.03103639276],"iteration":134,"passed_time":0.5470635253,"remaining_time":0.4903310116},
{"learn":[0.03093358201],"iteration":135,"passed_time":0.5514433996,"remaining_time":0.4865677055},
{"learn":[0.03078532291],"iteration":136,"passed_time":0.5555774814,"remaining_time":0.4825818999},
{"learn":[0.03052679426],"iteration":137,"passed_time":0.5601105409,"remaining_time":0.4789351002},
{"learn":[0.03033106601],"iteration":138,"passed_time":0.5638045591,"remaining_time":0.4745693052},
{"learn":[0.03013629414],"iteration":139,"passed_time":0.5684032612,"remaining_time":0.4709627022},
{"learn":[0.03003005303],"iteration":140,"passed_time":0.5722081408,"remaining_time":0.4666945829},
{"learn":[0.02984623093],"iteration":141,"passed_time":0.5762103246,"remaining_time":0.4625913874},
{"learn":[0.02968649513],"iteration":142,"passed_time":0.5800817001,"remaining_time":0.4583862385},
{"learn":[0.02944744209],"iteration":143,"passed_time":0.584501082,"remaining_time":0.4546119527},
{"learn":[0.02916900311],"iteration":144,"passed_time":0.5886787189,"remaining_time":0.450643709},
{"learn":[0.02895641022],"iteration":145,"passed_time":0.5922977018,"remaining_time":0.4462516931},
{"learn":[0.028782924],"iteration":146,"passed_time":0.5961631419,"remaining_time":0.4420529419},
{"learn":[0.02859326606],"iteration":147,"passed_time":0.6000829507,"remaining_time":0.4378983694},
{"learn":[0.02845141715],"iteration":148,"passed_time":0.6038514373,"remaining_time":0.4336382805},
{"learn":[0.0281536949],"iteration":149,"passed_time":0.6080314206,"remaining_time":0.4296755372},
{"learn":[0.02805498109],"iteration":150,"passed_time":0.6125511094,"remaining_time":0.4259461357},
{"learn":[0.02795998482],"iteration":151,"passed_time":0.6167786029,"remaining_time":0.4220064125},
{"learn":[0.02761822378],"iteration":152,"passed_time":0.6213415677,"remaining_time":0.4182887678},
{"learn":[0.02739811676],"iteration":153,"passed_time":0.625524495,"remaining_time":0.4143084317},
{"learn":[0.02731638351],"iteration":154,"passed_time":0.6298123148,"remaining_time":0.4103938309},
{"learn":[0.02705088611],"iteration":155,"passed_time":0.6345273352,"remaining_time":0.4067482918},
{"learn":[0.02679655979],"iteration":156,"passed_time":0.6422070376,"remaining_time":0.4049585779},
{"learn":[0.02663841798],"iteration":157,"passed_time":0.6496589109,"remaining_time":0.4029529953},
{"learn":[0.02642352501],"iteration":158,"passed_time":0.6530653561,"remaining_time":0.3984109405},
{"learn":[0.02635438029],"iteration":159,"passed_time":0.6568108291,"remaining_time":0.3940864974},
{"learn":[0.02594178042],"iteration":160,"passed_time":0.6609260041,"remaining_time":0.3899873937},
{"learn":[0.02587586055],"iteration":161,"passed_time":0.664878847,"remaining_time":0.3857938989},
{"learn":[0.02578808069],"iteration":162,"passed_time":0.6685877045,"remaining_time":0.3814641504},
{"learn":[0.02553416274],"iteration":163,"passed_time":0.6720981575,"remaining_time":0.3770306737},
{"learn":[0.02542117419],"iteration":164,"passed_time":0.6761415418,"remaining_time":0.3729023049},
{"learn":[0.02520541705],"iteration":165,"passed_time":0.6804332287,"remaining_time":0.3689095818},
{"learn":[0.02491046649],"iteration":166,"passed_time":0.6848772721,"remaining_time":0.3649944743},
{"learn":[0.02479533858],"iteration":167,"passed_time":0.6898047915,"remaining_time":0.3613263193},
{"learn":[0.02452358907],"iteration":168,"passed_time":0.6943296615,"remaining_time":0.3574359796},
{"learn":[0.02448289369],"iteration":169,"passed_time":0.6992539954,"remaining_time":0.3537402565},
{"learn":[0.02431365458],"iteration":170,"passed_time":0.7033829902,"remaining_time":0.3496348197},
{"learn":[0.02401718908],"iteration":171,"passed_time":0.7086357535,"remaining_time":0.3460779261},
{"learn":[0.02382454868],"iteration":172,"passed_time":0.7126273361,"remaining_time":0.341896352},
{"learn":[0.02374850371],"iteration":173,"passed_time":0.7174724588,"remaining_time":0.3381192047},
{"learn":[0.02368548463],"iteration":174,"passed_time":0.7210876678,"remaining_time":0.3337605777},
{"learn":[0.02361915112],"iteration":175,"passed_time":0.7254546187,"remaining_time":0.3297520994},
{"learn":[0.02341350064],"iteration":176,"passed_time":0.7295909709,"remaining_time":0.325636648},
{"learn":[0.02323652872],"iteration":177,"passed_time":0.7333267384,"remaining_time":0.3213454247},
{"learn":[0.02301814216],"iteration":178,"passed_time":0.737213555,"remaining_time":0.317125384},
{"learn":[0.02291783699],"iteration":179,"passed_time":0.7415645749,"remaining_time":0.3131050427},
{"learn":[0.02270338402],"iteration":180,"passed_time":0.7458032203,"remaining_time":0.3090344836},
{"learn":[0.02265140955],"iteration":181,"passed_time":0.7498303758,"remaining_time":0.3048760869},
{"learn":[0.02242391225],"iteration":182,"passed_time":0.7544504354,"remaining_time":0.3009556382},
{"learn":[0.02223818263],"iteration":183,"passed_time":0.7588942933,"remaining_time":0.2969586365},
{"learn":[0.02221289754],"iteration":184,"passed_time":0.7628006478,"remaining_time":0.2927505189},
{"learn":[0.02205618768],"iteration":185,"passed_time":0.7671305738,"remaining_time":0.2887050547},
{"learn":[0.02195522516],"iteration":186,"passed_time":0.771695146,"remaining_time":0.2847431287},
{"learn":[0.0217512174],"iteration":187,"passed_time":0.7757933599,"remaining_time":0.2806061089},
{"learn":[0.0216174583],"iteration":188,"passed_time":0.7795601914,"remaining_time":0.2763520255},
{"learn":[0.02148240952],"iteration":189,"passed_time":0.7838512402,"remaining_time":0.2722851677},
{"learn":[0.02122655245],"iteration":190,"passed_time":0.7878310533,"remaining_time":0.2681100443},
{"learn":[0.02106676132],"iteration":191,"passed_time":0.7918171794,"remaining_time":0.2639390598},
{"learn":[0.02097872589],"iteration":192,"passed_time":0.7952427652,"remaining_time":0.2595870166},
{"learn":[0.02081606691],"iteration":193,"passed_time":0.799078657,"remaining_time":0.2553756533},
{"learn":[0.02078787972],"iteration":194,"passed_time":0.803333757,"remaining_time":0.2512992778},
{"learn":[0.02051895327],"iteration":195,"passed_time":0.8071492033,"remaining_time":0.2470864908},
{"learn":[0.02038478843],"iteration":196,"passed_time":0.810891592,"remaining_time":0.2428558575},
{"learn":[0.02032829943],"iteration":197,"passed_time":0.8144822284,"remaining_time":0.2385857033},
{"learn":[0.0202360406],"iteration":198,"passed_time":0.8182758926,"remaining_time":0.234380532},
{"learn":[0.02019766506],"iteration":199,"passed_time":0.8226193269,"remaining_time":0.2303334115},
{"learn":[0.02013698691],"iteration":200,"passed_time":0.8265703748,"remaining_time":0.2261759732},
{"learn":[0.02007745879],"iteration":201,"passed_time":0.8304693312,"remaining_time":0.2220066529},
{"learn":[0.0198722404],"iteration":202,"passed_time":0.8340473461,"remaining_time":0.2177562037},
{"learn":[0.01978576602],"iteration":203,"passed_time":0.8378518692,"remaining_time":0.2135700843},
{"learn":[0.01971675435],"iteration":204,"passed_time":0.8419924001,"remaining_time":0.20947128},
{"learn":[0.01964400538],"iteration":205,"passed_time":0.8457397669,"remaining_time":0.2052766424},
{"learn":[0.01951882218],"iteration":206,"passed_time":0.8500049064,"remaining_time":0.2012088909},
{"learn":[0.01937974101],"iteration":207,"passed_time":0.8537097497,"remaining_time":0.1970099422},
{"learn":[0.0193068827],"iteration":208,"passed_time":0.8576240201,"remaining_time":0.1928628179},
{"learn":[0.01919481234],"iteration":209,"passed_time":0.8615210315,"remaining_time":0.1887141307},
{"learn":[0.01906836977],"iteration":210,"passed_time":0.8655862721,"remaining_time":0.1846037073},
{"learn":[0.01901937249],"iteration":211,"passed_time":0.8698055119,"remaining_time":0.1805256723},
{"learn":[0.01894103798],"iteration":212,"passed_time":0.8733538886,"remaining_time":0.1763108789},
{"learn":[0.01889347266],"iteration":213,"passed_time":0.8771202071,"remaining_time":0.1721450874},
{"learn":[0.01878173955],"iteration":214,"passed_time":0.8816075832,"remaining_time":0.1681205159},
{"learn":[0.01868440104],"iteration":215,"passed_time":0.8855569881,"remaining_time":0.1639920348},
{"learn":[0.01857348336],"iteration":216,"passed_time":0.889165631,"remaining_time":0.1598039613},
{"learn":[0.01838643244],"iteration":217,"passed_time":0.8931693797,"remaining_time":0.1556900754},
{"learn":[0.0182904126],"iteration":218,"passed_time":0.8971275828,"remaining_time":0.1515695003},
{"learn":[0.0182636613],"iteration":219,"passed_time":0.9010063833,"remaining_time":0.1474374082},
{"learn":[0.01815066617],"iteration":220,"passed_time":0.9087078529,"remaining_time":0.1439130084},
{"learn":[0.01807027924],"iteration":221,"passed_time":0.9128801776,"remaining_time":0.1398104776},
{"learn":[0.01803709799],"iteration":222,"passed_time":0.9168652206,"remaining_time":0.1356796066},
{"learn":[0.01796720634],"iteration":223,"passed_time":0.9205084771,"remaining_time":0.131501211},
{"learn":[0.0178715672],"iteration":224,"passed_time":0.9243100247,"remaining_time":0.1273493812},
{"learn":[0.01780813843],"iteration":225,"passed_time":0.9277684719,"remaining_time":0.1231551069},
{"learn":[0.01777513371],"iteration":226,"passed_time":0.9316314305,"remaining_time":0.1190189933},
{"learn":[0.0176372263],"iteration":227,"passed_time":0.9352504345,"remaining_time":0.1148553165},
{"learn":[0.01750598859],"iteration":228,"passed_time":0.9395042598,"remaining_time":0.1107712446},
{"learn":[0.01738582711],"iteration":229,"passed_time":0.9466500081,"remaining_time":0.1070126096},
{"learn":[0.01729449042],"iteration":230,"passed_time":0.9540367156,"remaining_time":0.1032507268},
{"learn":[0.01709231113],"iteration":231,"passed_time":0.9609154075,"remaining_time":0.09940504215},
{"learn":[0.01705530564],"iteration":232,"passed_time":0.9648042857,"remaining_time":0.0952381913},
{"learn":[0.01698001683],"iteration":233,"passed_time":0.9728680382,"remaining_time":0.09146622582},
{"learn":[0.01691206562],"iteration":234,"passed_time":0.9799059441,"remaining_time":0.08756606309},
{"learn":[0.01684120967],"iteration":235,"passed_time":0.9869343038,"remaining_time":0.08363850032},
{"learn":[0.01679936689],"iteration":236,"passed_time":0.9933627808,"remaining_time":0.07963667863},
{"learn":[0.01668677486],"iteration":237,"passed_time":0.9970635815,"remaining_time":0.07540817003},
{"learn":[0.01664677109],"iteration":238,"passed_time":1.001069912,"remaining_time":0.07120580963},
{"learn":[0.01660815844],"iteration":239,"passed_time":1.004595569,"remaining_time":0.06697303793},
{"learn":[0.01652597202],"iteration":240,"passed_time":1.008386827,"remaining_time":0.06276266561},
{"learn":[0.01651328468],"iteration":241,"passed_time":1.011983057,"remaining_time":0.05854447436},
{"learn":[0.01647894944],"iteration":242,"passed_time":1.015694545,"remaining_time":0.05433756823},
{"learn":[0.01640338399],"iteration":243,"passed_time":1.019743892,"remaining_time":0.05015133895},
{"learn":[0.01633033334],"iteration":244,"passed_time":1.023206726,"remaining_time":0.04593989381},
{"learn":[0.01630845358],"iteration":245,"passed_time":1.02721246,"remaining_time":0.04175660405},
{"learn":[0.01625518417],"iteration":246,"passed_time":1.030951622,"remaining_time":0.03756503887},
{"learn":[0.01613265279],"iteration":247,"passed_time":1.034704959,"remaining_time":0.03337757934},
{"learn":[0.01609865347],"iteration":248,"passed_time":1.038483306,"remaining_time":0.02919430981},
{"learn":[0.01597300262],"iteration":249,"passed_time":1.042286136,"remaining_time":0.02501486725},
{"learn":[0.0159126999],"iteration":250,"passed_time":1.04550236,"remaining_time":0.02082674024},
{"learn":[0.01584720027],"iteration":251,"passed_time":1.049409009,"remaining_time":0.01665728585},
{"learn":[0.01569216871],"iteration":252,"passed_time":1.053024108,"remaining_time":0.01248645187},
{"learn":[0.01558275675],"iteration":253,"passed_time":1.056837086,"remaining_time":0.00832155186},
{"learn":[0.0155011763],"iteration":254,"passed_time":1.060645125,"remaining_time":0.004159392649},
{"learn":[0.01542485469],"iteration":255,"passed_time":1.06416479,"remaining_time":0}
]}